{"Memes":[{"Name":"adada","Category":"ssss","Source":"C:\\Users\\Viktoria\\source\\repos\\kursovaya99\\MemeFinder\\Memes\\1.jpg","HashTag":"#sssss"},{"Name":"eating and sleep","Category":"dogs ","Source":"C:\\Users\\Viktoria\\source\\repos\\kursovaya99\\MemeFinder\\Memes\\eating and sleep.png","HashTag":"#error"},{"Name":"eat","Category":"dogs","Source":"C:\\Users\\Viktoria\\source\\repos\\kursovaya99\\MemeFinder\\Memes\\eat.png","HashTag":"#error"},{"Name":"error","Category":"dogs","Source":"C:\\Users\\Viktoria\\source\\repos\\kursovaya99\\MemeFinder\\Memes\\error.png","HashTag":"#error"},{"Name":"error man","Category":"dogs","Source":"C:\\Users\\Viktoria\\source\\repos\\kursovaya99\\MemeFinder\\Memes\\error man.png","HashTag":"#error"},{"Name":"double error","Category":"dogs","Source":"C:\\Users\\Viktoria\\source\\repos\\kursovaya99\\MemeFinder\\Memes\\double error.png","HashTag":"#error"},{"Name":"oaoaooaoa","Category":"dogs","Source":"C:\\Users\\Viktoria\\source\\repos\\kursovaya99\\MemeFinder\\Memes\\oaoaooaoa.png","HashTag":"#error"},{"Name":"pixar","Category":"dogs","Source":"C:\\Users\\Viktoria\\source\\repos\\kursovaya99\\MemeFinder\\Memes\\pixar.png","HashTag":"#error"},{"Name":"0.5 dogs","Category":"dogs","Source":"C:\\Users\\Viktoria\\source\\repos\\kursovaya99\\MemeFinder\\Memes\\0.5 dogs.png","HashTag":"#error"},{"Name":"hi hi hi","Category":"dogs","Source":"C:\\Users\\Viktoria\\source\\repos\\kursovaya99\\MemeFinder\\Memes\\hi hi hi.png","HashTag":"#agner"},{"Name":"happy dogs","Category":"dogs","Source":"C:\\Users\\Viktoria\\source\\repos\\kursovaya99\\MemeFinder\\Memes\\happy dogs.png","HashTag":"#happy"},{"Name":"happy kus","Category":"dogs","Source":"C:\\Users\\Viktoria\\source\\repos\\kursovaya99\\MemeFinder\\Memes\\happy kus.png","HashTag":"#happy"},{"Name":"nice!","Category":"dogs","Source":"C:\\Users\\Viktoria\\source\\repos\\kursovaya99\\MemeFinder\\Memes\\nice!.png","HashTag":"#happy"},{"Name":"aaaaaaaa","Category":"dogs","Source":"C:\\Users\\Viktoria\\source\\repos\\kursovaya99\\MemeFinder\\Memes\\aaaaaaaa.png","HashTag":"#panic"},{"Name":"AaAaAaAa","Category":"dogs","Source":"C:\\Users\\Viktoria\\source\\repos\\kursovaya99\\MemeFinder\\Memes\\AaAaAaAa.png","HashTag":"#panic"},{"Name":"panicaaaaaa","Category":"dogs","Source":"C:\\Users\\Viktoria\\source\\repos\\kursovaya99\\MemeFinder\\Memes\\panicaaaaaa.png","HashTag":"#panic"},{"Name":"salto","Category":"dogs","Source":"C:\\Users\\Viktoria\\source\\repos\\kursovaya99\\MemeFinder\\Memes\\salto.png","HashTag":"#panic"},{"Name":"hnik","Category":"dogs","Source":"C:\\Users\\Viktoria\\source\\repos\\kursovaya99\\MemeFinder\\Memes\\hnik.png","HashTag":"#sry"},{"Name":"oy mom","Category":"dogs","Source":"C:\\Users\\Viktoria\\source\\repos\\kursovaya99\\MemeFinder\\Memes\\oy mom.png","HashTag":"#sry"},{"Name":"sonne","Category":"dogs","Source":"C:\\Users\\Viktoria\\source\\repos\\kursovaya99\\MemeFinder\\Memes\\sonne.png","HashTag":"#sry"},{"Name":"war","Category":"dogs","Source":"C:\\Users\\Viktoria\\source\\repos\\kursovaya99\\MemeFinder\\Memes\\war.png","HashTag":"#sry"},{"Name":"warr","Category":"dogss","Source":"C:\\Users\\rodje\\source\\repos\\kursovaya99999\\MemeFinder\\Memes\\warr.png","HashTag":"#13413"},{"Name":"123","Category":"123","Source":"C:\\Users\\rodje\\source\\repos\\kursovaya99999\\MemeFinder\\Memes\\123.png","HashTag":"#123"},{"Name":"3231","Category":"23124","Source":"C:\\Users\\rodje\\source\\repos\\kursovaya99999\\MemeFinder\\Memes\\3231.png","HashTag":"#244242"},{"Name":"1341341","Category":"13413","Source":"C:\\Users\\rodje\\source\\repos\\kursovaya99999\\MemeFinder\\Memes\\1341341.png","HashTag":"#1341"},{"Name":"13441","Category":"41324","Source":"C:\\Users\\rodje\\source\\repos\\kursovaya99999\\MemeFinder\\Memes\\13441.png","HashTag":"#4134"},{"Name":"342342","Category":"2343","Source":"C:\\Users\\rodje\\source\\repos\\kursovaya99999\\MemeFinder\\Memes\\342342.png","HashTag":"#23423"},{"Name":"242432","Category":"24345","Source":"C:\\Users\\rodje\\source\\repos\\kursovaya99999\\MemeFinder\\Memes\\242432.png","HashTag":"#234234"},{"Name":"423525","Category":"352342","Source":"C:\\Users\\rodje\\source\\repos\\kursovaya99999\\MemeFinder\\Memes\\423525.png","HashTag":"#23423"},{"Name":"234234","Category":"252452","Source":"C:\\Users\\rodje\\source\\repos\\kursovaya99999\\MemeFinder\\Memes\\234234.png","HashTag":"#234234"},{"Name":"234265","Category":"5456","Source":"C:\\Users\\rodje\\source\\repos\\kursovaya99999\\MemeFinder\\Memes\\234265.png","HashTag":"#456456"}]}